iy/__init__.py
iy-0.0.6.dist-info/licenses/LICENSE
iy-0.0.6.dist-info/METADATA
iy-0.0.6.dist-info/WHEEL
iy-0.0.6.dist-info/top_level.txt
iy-0.0.6.dist-info/RECORD
