Metadata-Version: 2.4
Name: iy
Version: 0.0.6
Summary: Includes functions to diagnose duplicates in adwords elements
Home-page: https://github.com/t-c-w/iy
Author: Thor Whalen
License: apache-2.0
Platform: any
License-File: LICENSE
Dynamic: license-file
